NMODL-0.5.data/scripts/find_libpython.py
NMODL-0.5.data/scripts/nmodl
nmodl/visitor.py
nmodl/_nmodl.cpython-311-x86_64-linux-gnu.so
nmodl/dsl.py
nmodl/ode.py
nmodl/symtab.py
nmodl/ast.py
nmodl/__init__.py
nmodl/.data/bin/nmodl
nmodl/.data/lib/libpywrapper.so
nmodl/.data/share/nmodl/nrnunits.lib
nmodl/.data/include/nmodl.hpp
nmodl/.data/include/crout/crout.hpp
nmodl/.data/include/Eigen/SparseLU
nmodl/.data/include/Eigen/CholmodSupport
nmodl/.data/include/Eigen/SparseCholesky
nmodl/.data/include/Eigen/SPQRSupport
nmodl/.data/include/Eigen/StdList
nmodl/.data/include/Eigen/SparseCore
nmodl/.data/include/Eigen/StdVector
nmodl/.data/include/Eigen/Geometry
nmodl/.data/include/Eigen/StdDeque
nmodl/.data/include/Eigen/LU
nmodl/.data/include/Eigen/PaStiXSupport
nmodl/.data/include/Eigen/Core
nmodl/.data/include/Eigen/Householder
nmodl/.data/include/Eigen/SVD
nmodl/.data/include/Eigen/KLUSupport
nmodl/.data/include/Eigen/Eigen
nmodl/.data/include/Eigen/IterativeLinearSolvers
nmodl/.data/include/Eigen/PardisoSupport
nmodl/.data/include/Eigen/Cholesky
nmodl/.data/include/Eigen/QtAlignedMalloc
nmodl/.data/include/Eigen/SparseQR
nmodl/.data/include/Eigen/OrderingMethods
nmodl/.data/include/Eigen/QR
nmodl/.data/include/Eigen/Jacobi
nmodl/.data/include/Eigen/UmfPackSupport
nmodl/.data/include/Eigen/Eigenvalues
nmodl/.data/include/Eigen/Sparse
nmodl/.data/include/Eigen/SuperLUSupport
nmodl/.data/include/Eigen/MetisSupport
nmodl/.data/include/Eigen/Dense
nmodl/.data/include/Eigen/src/SparseLU/SparseLU_kernel_bmod.h
nmodl/.data/include/Eigen/src/SparseLU/SparseLU_Structs.h
nmodl/.data/include/Eigen/src/SparseLU/SparseLU_panel_bmod.h
nmodl/.data/include/Eigen/src/SparseLU/SparseLU_heap_relax_snode.h
nmodl/.data/include/Eigen/src/SparseLU/SparseLU_pivotL.h
nmodl/.data/include/Eigen/src/SparseLU/SparseLU_copy_to_ucol.h
nmodl/.data/include/Eigen/src/SparseLU/SparseLU_relax_snode.h
NMODL-0.5.dist-info/METADATA
NMODL-0.5.dist-info/WHEEL
NMODL-0.5.dist-info/top_level.txt
NMODL-0.5.dist-info/RECORD
NMODL-0.5.dist-info/LICENSE
NMODL-0.5.dist-info/AUTHORS.txt
