Metadata-Version: 2.1
Name: NMODL
Version: 0.5
Summary: NEURON Modeling Language Source-to-Source Compiler Framework
Author: Blue Brain Project
Author-email: bbp-ou-hpc@groupes.epfl.ch
License-File: LICENSE
License-File: AUTHORS.txt
Requires-Dist: PyYAML (>=3.13)
Requires-Dist: sympy (>=1.3)
